learnrl/__init__.py
learnrl/agent.py
learnrl/envs.py
learnrl/playground.py
learnrl/callbacks/__init__.py
learnrl/callbacks/callback.py
learnrl/callbacks/logger.py
learnrl/callbacks/logging_callback.py
learnrl/callbacks/tensorboard.py
learnrl/callbacks/wandb.py
tests/integration/__init__.py
tests/integration/callbacks/__init__.py
tests/integration/callbacks/test_logging.py
tests/unit/__init__.py
tests/unit/test_agent.py
tests/unit/test_envs.py
tests/unit/test_playground.py
tests/unit/callbacks/__init__.py
tests/unit/callbacks/test_callback.py
tests/unit/callbacks/test_logging.py
tests/unit/callbacks/test_tensorboard.py
tests/unit/callbacks/test_wandb.py
learnrl-1.0.2.dist-info/COPYING
learnrl-1.0.2.dist-info/COPYING.LESSER
learnrl-1.0.2.dist-info/LICENCE
learnrl-1.0.2.dist-info/METADATA
learnrl-1.0.2.dist-info/WHEEL
learnrl-1.0.2.dist-info/top_level.txt
learnrl-1.0.2.dist-info/RECORD
