Metadata-Version: 2.1
Name: learnrl
Version: 1.0.2
Summary: A package to learn about Reinforcement Learning
Home-page: https://github.com/MathisFederico/LearnRL
Author: Mathïs Fédérico
Author-email: mathfederico@gmail.com
License: UNKNOWN
Platform: UNKNOWN
Classifier: Programming Language :: Python :: 3
Classifier: License :: OSI Approved :: GNU Lesser General Public License v3 or later (LGPLv3+)
Classifier: Operating System :: OS Independent
Requires-Python: >=3.6
License-File: LICENCE
License-File: COPYING
License-File: COPYING.LESSER
Requires-Dist: numpy
Requires-Dist: gym (==0.17.3)
